zipFly/BaseFile.py
zipFly/Compressor.py
zipFly/EmptyFolder.py
zipFly/FilePrefetcher.py
zipFly/GenFile.py
zipFly/LocalFile.py
zipFly/ZipBase.py
zipFly/ZipFly.py
zipFly/__init__.py
zipFly/consts.py
zipfly64-1.3.1.dist-info/licenses/LICENSE
zipfly64-1.3.1.dist-info/METADATA
zipfly64-1.3.1.dist-info/WHEEL
zipfly64-1.3.1.dist-info/top_level.txt
zipfly64-1.3.1.dist-info/RECORD
