Metadata-Version: 2.4
Name: zipFly64
Version: 1.3.1
Summary: Stream zip64 archives on the fly.
Author: Pamparampampam
License: MIT License
Project-URL: Github, https://github.com/pam-param-pam/ZipFly
Keywords: zip64,zip,streaming,zipfly,zipfly64
Classifier: License :: OSI Approved :: MIT License
Classifier: Programming Language :: Python
Classifier: Programming Language :: Python :: 3
Requires-Python: >=3.7
License-File: LICENSE
Requires-Dist: aiofiles>=24.1.0
Dynamic: license-file
